tofspec/.DS_Store
tofspec/__init__.py
tofspec/cli/__init__.py
tofspec/cli/commands/concat.py
tofspec/cli/commands/config.py
tofspec/cli/commands/integrate_peaks.py
tofspec/cli/commands/label.py
tofspec/cli/commands/load.py
tofspec/cli/commands/merge.py
tofspec/config/peak-list.yml
tofspec/db/build_db.py
tofspec/db/database.feather
tofspec/db/substructures.yml
tofspec/exceptions.py
tofspec/integrate.py
tofspec/load.py
tofspec/models.py
tofspec/utils.py
py_tofspec-0.2.1.dist-info/entry_points.txt
py_tofspec-0.2.1.dist-info/LICENSE.md
py_tofspec-0.2.1.dist-info/WHEEL
py_tofspec-0.2.1.dist-info/METADATA
py_tofspec-0.2.1.dist-info/RECORD
